quickmachotkey/__init__.py
quickmachotkey/constants.py
quickmachotkey/py.typed
quickmachotkey/_MinimalHIToolbox/__init__.py
quickmachotkey/_MinimalHIToolbox/_metadata.py
quickmachotkey/configurators/__init__.py
quickmachotkey/configurators/jsonfile.py
quickmachotkey-2025.7.28.dist-info/licenses/LICENSE
quickmachotkey-2025.7.28.dist-info/METADATA
quickmachotkey-2025.7.28.dist-info/WHEEL
quickmachotkey-2025.7.28.dist-info/top_level.txt
quickmachotkey-2025.7.28.dist-info/RECORD
