Metadata-Version: 2.4
Name: quickmachotkey
Version: 2025.7.28
Summary: Bind a global hotkey, on macOS, in Python
Project-URL: Source Code, https://github.com/glyph/QuickMacHotKey
License-File: LICENSE
Requires-Dist: pyobjc-core
Requires-Dist: pyobjc-framework-Cocoa
Dynamic: license-file
